Couchapp-1.0.2.data/data/couchapp/LICENSE
Couchapp-1.0.2.data/data/couchapp/MANIFEST.in
Couchapp-1.0.2.data/data/couchapp/NOTICE
Couchapp-1.0.2.data/data/couchapp/README.rst
Couchapp-1.0.2.data/data/couchapp/THANKS
Couchapp-1.0.2.data/scripts/couchapp
Couchapp-1.0.2.dist-info/DESCRIPTION.rst
Couchapp-1.0.2.dist-info/METADATA
Couchapp-1.0.2.dist-info/RECORD
Couchapp-1.0.2.dist-info/WHEEL
Couchapp-1.0.2.dist-info/metadata.json
Couchapp-1.0.2.dist-info/pbr.json
Couchapp-1.0.2.dist-info/top_level.txt
couchapp/__init__.py
couchapp/client.py
couchapp/clone_app.py
couchapp/commands.py
couchapp/config.py
couchapp/dispatch.py
couchapp/errors.py
couchapp/generator.py
couchapp/localdoc.py
couchapp/macros.py
couchapp/util.py
couchapp/autopush/__init__.py
couchapp/autopush/command.py
couchapp/autopush/handler.py
couchapp/autopush/watcher.py
couchapp/autopush/winwatcher.py
couchapp/hooks/__init__.py
couchapp/hooks/compress/__init__.py
couchapp/hooks/compress/compress_css.py
couchapp/hooks/compress/default.py
couchapp/hooks/compress/jsmin.py
couchapp/hooks/compress/yuicompressor.py
couchapp/templates/app/README.md
couchapp/templates/app/couchapp.json
couchapp/templates/app/language
couchapp/templates/app/_attachments/index.html
couchapp/templates/app/_attachments/script/app.js
couchapp/templates/app/_attachments/style/main.css
couchapp/templates/app/views/recent-items/map.js
couchapp/templates/functions/filter.js
couchapp/templates/functions/list.js
couchapp/templates/functions/map.js
couchapp/templates/functions/reduce.js
couchapp/templates/functions/show.js
couchapp/templates/functions/spatial.js
couchapp/templates/functions/update.js
couchapp/templates/functions/validate_doc_update.js
couchapp/templates/vendor/couchapp/metadata.json
couchapp/templates/vendor/couchapp/_attachments/jquery.couch.app.js
couchapp/templates/vendor/couchapp/_attachments/jquery.couch.app.util.js
couchapp/templates/vendor/couchapp/_attachments/jquery.couchForm.js
couchapp/templates/vendor/couchapp/_attachments/jquery.couchLogin.js
couchapp/templates/vendor/couchapp/_attachments/jquery.couchProfile.js
couchapp/templates/vendor/couchapp/_attachments/jquery.mustache.js
