Metadata-Version: 2.0
Name: Couchapp
Version: 1.0.2
Summary: Standalone CouchDB Application Development Made Simple.
Home-page: http://github.com/couchapp/couchapp/tree/master
Author: Benoit Chesneau
Author-email: benoitc@e-engura.org
License: Apache License 2
Keywords: couchdb couchapp
Platform: any
Classifier: License :: OSI Approved :: Apache Software License
Classifier: Intended Audience :: Developers
Classifier: Intended Audience :: System Administrators
Classifier: Development Status :: 4 - Beta
Classifier: Programming Language :: Python :: 2
Classifier: Programming Language :: Python :: 2.6
Classifier: Programming Language :: Python :: 2.7
Classifier: Operating System :: OS Independent
Classifier: Topic :: Database
Classifier: Topic :: Utilities
Requires-Dist: restkit (==4.2.2)
Requires-Dist: watchdog (==0.6.0)
